mockupdb/__init__.py
mockupdb/__main__.py
mockupdb/server.pem
mockupdb-1.8.1.dist-info/AUTHORS.rst
mockupdb-1.8.1.dist-info/LICENSE
mockupdb-1.8.1.dist-info/METADATA
mockupdb-1.8.1.dist-info/WHEEL
mockupdb-1.8.1.dist-info/top_level.txt
mockupdb-1.8.1.dist-info/RECORD
