Metadata-Version: 1.2
Name: mockupdb
Version: 1.8.1
Summary: MongoDB Wire Protocol server library
Home-page: https://github.com/ajdavis/mongo-mockup-db
Author: A. Jesse Jiryu Davis
Author-email: jesse@mongodb.com
License: Apache License, Version 2.0
Keywords: mongo,mongodb,wire protocol,mockupdb,mock
Platform: UNKNOWN
Classifier: Development Status :: 5 - Production/Stable
Classifier: Intended Audience :: Developers
Classifier: License :: OSI Approved :: Apache Software License
Classifier: Natural Language :: English
Classifier: Programming Language :: Python :: 2
Classifier: Programming Language :: Python :: 2.7
Classifier: Programming Language :: Python :: 3
Classifier: Programming Language :: Python :: 3.4
Classifier: Programming Language :: Python :: 3.5
Classifier: Programming Language :: Python :: 3.6
Classifier: Programming Language :: Python :: 3.7
Classifier: Programming Language :: Python :: 3.8
Requires-Python: >=2.7,!=3.0.*,!=3.1.*,!=3.2.*,!=3.3.*
